tga/__init__.py
tga/color.py
tga/image.py
tga/py.typed
tga-0.0.2.dist-info/LICENSE.txt
tga-0.0.2.dist-info/METADATA
tga-0.0.2.dist-info/WHEEL
tga-0.0.2.dist-info/top_level.txt
tga-0.0.2.dist-info/RECORD
