Metadata-Version: 2.1
Name: tga
Version: 0.0.2
Summary: A Python package which supports working with TGA, also known as TARGA (Truevision Advanced Raster Graphics Adapter), files.
Home-page: https://github.com/jteppinette/python-tga
Author: Joshua Taylor Eppinette
Author-email: jteppinette@jteppinette.com
License: MIT
Platform: UNKNOWN
Requires-Python: >=3.6
License-File: LICENSE.txt
